flow_prompt/__init__.py
flow_prompt/ai_models/__init__.py
flow_prompt/ai_models/ai_model.py
flow_prompt/ai_models/attempt_to_call.py
flow_prompt/ai_models/behaviour.py
flow_prompt/ai_models/claude/__init__.py
flow_prompt/ai_models/claude/claude_model.py
flow_prompt/ai_models/claude/constants.py
flow_prompt/ai_models/claude/responses.py
flow_prompt/ai_models/constants.py
flow_prompt/ai_models/gemini/__init__.py
flow_prompt/ai_models/gemini/gemini_model.py
flow_prompt/ai_models/gemini/responses.py
flow_prompt/ai_models/openai/__init__.py
flow_prompt/ai_models/openai/azure_models.py
flow_prompt/ai_models/openai/behaviours.py
flow_prompt/ai_models/openai/exceptions.py
flow_prompt/ai_models/openai/openai_models.py
flow_prompt/ai_models/openai/responses.py
flow_prompt/ai_models/openai/utils.py
flow_prompt/ai_models/utils.py
flow_prompt/exceptions.py
flow_prompt/prompt/__init__.py
flow_prompt/prompt/base_prompt.py
flow_prompt/prompt/chat.py
flow_prompt/prompt/flow_prompt.py
flow_prompt/prompt/pipe_prompt.py
flow_prompt/prompt/user_prompt.py
flow_prompt/response_parsers/response_parser.py
flow_prompt/responses.py
flow_prompt/services/__init__.py
flow_prompt/services/flow_prompt/__init__.py
flow_prompt/services/SaveWorker.py
flow_prompt/settings.py
flow_prompt/utils.py
flow_prompt-0.1.31.dist-info/LICENSE
flow_prompt-0.1.31.dist-info/METADATA
flow_prompt-0.1.31.dist-info/WHEEL
flow_prompt-0.1.31.dist-info/RECORD
