Metadata-Version: 2.1
Name: flow-prompt
Version: 0.1.31
Summary: 
Author: Flow-prompt Engineering Team
Author-email: engineering@flow-prompt.com
Requires-Python: >=3.9,<4.0
Classifier: Programming Language :: Python :: 3
Classifier: Programming Language :: Python :: 3.9
Classifier: Programming Language :: Python :: 3.10
Classifier: Programming Language :: Python :: 3.11
Classifier: Programming Language :: Python :: 3.12
Requires-Dist: anthropic (>=0.31.2,<0.32.0)
Requires-Dist: google-generativeai (>=0.7.2,<0.8.0)
Requires-Dist: openai (>=1.35.15,<2.0.0)
Requires-Dist: pyyaml (>=6.0.1,<7.0.0)
Requires-Dist: tiktoken (>=0.5.2)
